abhicsbsml/__init__.py
abhicsbsml/classification.py
abhicsbsml/clustering.py
abhicsbsml/faces.py
abhicsbsml/regression.py
abhicsbsml/visuals.py
abhicsbsml-0.1.dist-info/licenses/LICENSE
abhicsbsml-0.1.dist-info/METADATA
abhicsbsml-0.1.dist-info/WHEEL
abhicsbsml-0.1.dist-info/top_level.txt
abhicsbsml-0.1.dist-info/RECORD
